replay/__init__.py
replay/admin.py
replay/middleware.py
replay/models.py
replay/tests.py
replay/views.py
replay/management/__init__.py
replay/management/commands/__init__.py
replay/management/commands/record.py
replay/management/commands/testscenario.py
replay/migrations/0001_initial.py
replay/migrations/0002_action_files.py
replay/migrations/0003_auto_20170217_2114.py
replay/migrations/0004_auto_20170217_2115.py
replay/migrations/0005_auto_20170222_0131.py
replay/migrations/0006_auto_20170225_0018.py
replay/migrations/0007_auto_20190104_0511.py
replay/migrations/__init__.py
django_replay-0.9.1.dist-info/LICENSE
django_replay-0.9.1.dist-info/METADATA
django_replay-0.9.1.dist-info/WHEEL
django_replay-0.9.1.dist-info/top_level.txt
django_replay-0.9.1.dist-info/RECORD
